nornir_nautobot/__init__.py
nornir_nautobot/constants.py
nornir_nautobot/exceptions.py
nornir_nautobot/plugins/__init__.py
nornir_nautobot/plugins/inventory/__init__.py
nornir_nautobot/plugins/inventory/nautobot.py
nornir_nautobot/plugins/processors/__init__.py
nornir_nautobot/plugins/processors/get_config.py
nornir_nautobot/plugins/tasks/dispatcher/__init__.py
nornir_nautobot/plugins/tasks/dispatcher/arista_eos.py
nornir_nautobot/plugins/tasks/dispatcher/cisco_asa.py
nornir_nautobot/plugins/tasks/dispatcher/cisco_ios.py
nornir_nautobot/plugins/tasks/dispatcher/cisco_nxos.py
nornir_nautobot/plugins/tasks/dispatcher/cisco_xr.py
nornir_nautobot/plugins/tasks/dispatcher/default.py
nornir_nautobot/plugins/tasks/dispatcher/extreme_exos.py
nornir_nautobot/plugins/tasks/dispatcher/juniper_junos.py
nornir_nautobot/plugins/tasks/dispatcher/mikrotik_routeros.py
nornir_nautobot/plugins/tasks/dispatcher/ruckus_fastiron.py
nornir_nautobot/plugins/tasks/dispatcher/ruckus_smartzone.py
nornir_nautobot/plugins/tasks/template_file.py
nornir_nautobot/utils/helpers.py
nornir_nautobot/utils/mock.py
nornir_nautobot-4.0.0.dist-info/METADATA
nornir_nautobot-4.0.0.dist-info/WHEEL
nornir_nautobot-4.0.0.dist-info/entry_points.txt
nornir_nautobot-4.0.0.dist-info/licenses/LICENSE
nornir_nautobot-4.0.0.dist-info/RECORD
