Metadata-Version: 2.4
Name: nornir-nautobot
Version: 4.0.0
Summary: Nornir Nautobot
License: Apache-2.0
License-File: LICENSE
Keywords: Nautobot,Nornir,Network Automation,Network Management
Author: Network to Code, LLC
Author-email: opensource@networktocode.com
Requires-Python: >=3.10,<3.14
Classifier: Development Status :: 5 - Production/Stable
Classifier: Intended Audience :: Developers
Classifier: License :: OSI Approved :: Apache Software License
Classifier: Programming Language :: Python :: 3
Classifier: Programming Language :: Python :: 3.10
Classifier: Programming Language :: Python :: 3.11
Classifier: Programming Language :: Python :: 3.12
Classifier: Programming Language :: Python :: 3.13
Provides-Extra: mikrotik-driver
Requires-Dist: httpx (>=0.23.0,<=0.27.0)
Requires-Dist: napalm (>=5.0.0,<6.0.0)
Requires-Dist: netmiko (>=4.4.0,<5.0.0)
Requires-Dist: netutils (>=1.14.1,<2.0.0)
Requires-Dist: nornir (>=3.3.0,<4.0.0)
Requires-Dist: nornir-napalm (>=0.5.0,<1.0.0)
Requires-Dist: nornir-netmiko (>=1.0.0,<2.0.0)
Requires-Dist: nornir-scrapli (>=2025.1.30,<2026.0.0)
Requires-Dist: nornir-utils (>=0,<1)
Requires-Dist: pynautobot (>=3.0.0,<4.0.0)
Requires-Dist: requests (>=2.30.1,<3.0.0)
Requires-Dist: routeros-api (>=0.17.0,<0.18.0) ; extra == "mikrotik-driver"
Requires-Dist: scrapli (>=2024.01.30)
Project-URL: Documentation, https://docs.nautobot.com/projects/nornir-nautobot/en/latest/
Project-URL: Homepage, https://github.com/nautobot/nornir-nautobot
Project-URL: Repository, https://github.com/nautobot/nornir-nautobot
